{
	"animations": [
		{
			"offsets": [
				0,
				0
			],
			"loop": true,
			"fps": 24,
			"anim": "idlalakoop",
			"indices": [
				10,
				11,
				12,
				12
			],
			"name": "xd"
		},
		{
			"offsets": [
				-9,
				10
			],
			"loop": true,
			"fps": 24,
			"anim": "singLEFskskoop",
			"indices": [
				12,
				13,
				14,
				15
			],
			"name": "bf-new left0002"
		},
		{
			"offsets": [
				0,
				27
			],
			"loop": true,
			"fps": 24,
			"anim": "singRIjskksp",
			"indices": [
				15,
				16,
				17,
				18
			],
			"name": "bf-new right0002"
		},
		{
			"offsets": [
				-6,
				50
			],
			"loop": true,
			"fps": 24,
			"anim": "singoop",
			"indices": [
				56,
				57,
				58,
				59
			],
			"name": "bf-new up0002"
		},
		{
			"loop": false,
			"offsets": [
				-15,
				-22
			],
			"anim": "singDOWN",
			"fps": 18,
			"name": "down",
			"indices": []
		},
		{
			"loop": false,
			"offsets": [
				-15,
				12
			],
			"anim": "singUP",
			"fps": 18,
			"name": "up",
			"indices": []
		},
		{
			"offsets": [
				-14,
				0
			],
			"loop": false,
			"fps": 24,
			"anim": "singUPmiss",
			"indices": [],
			"name": "missup"
		},
		{
			"offsets": [
				0,
				0
			],
			"loop": false,
			"fps": 24,
			"anim": "singODWNmiss",
			"indices": [],
			"name": "missdown"
		},
		{
			"offsets": [
				0,
				0
			],
			"loop": false,
			"fps": 24,
			"anim": "singLEFTmiss",
			"indices": [],
			"name": "missleft"
		},
		{
			"offsets": [
				0,
				0
			],
			"loop": false,
			"fps": 24,
			"anim": "singRIGHTmiss",
			"indices": [],
			"name": "missright"
		},
		{
			"offsets": [
				0,
				0
			],
			"loop": false,
			"fps": 24,
			"anim": "dodge",
			"indices": [],
			"name": "dodge"
		},
		{
			"loop": false,
			"offsets": [
				0,
				19
			],
			"anim": "idle",
			"fps": 12,
			"name": "idle",
			"indices": []
		},
		{
			"loop": false,
			"offsets": [
				-23,
				3
			],
			"anim": "singRIGHT",
			"fps": 24,
			"name": "right",
			"indices": []
		},
		{
			"loop": false,
			"offsets": [
				54,
				2
			],
			"anim": "singLEFT",
			"fps": 21,
			"name": "left",
			"indices": []
		}
	],
	"vocals_file": "",
	"no_antialiasing": false,
	"image": "characters/gaelcp",
	"position": [
		50,
		-80
	],
	"healthicon": "bf",
	"flip_x": true,
	"healthbar_colors": [
		0,
		170,
		255
	],
	"camera_position": [
		180,
		-160
	],
	"sing_duration": 6.2,
	"scale": 1.3,
	"_editor_isPlayer": true
}